country_viewport/__init__.py
country_viewport/viewports.csv
country_viewport-0.1.9.dist-info/LICENSE.txt
country_viewport-0.1.9.dist-info/METADATA
country_viewport-0.1.9.dist-info/WHEEL
country_viewport-0.1.9.dist-info/top_level.txt
country_viewport-0.1.9.dist-info/RECORD
