Metadata-Version: 2.1
Name: country-viewport
Version: 0.1.9
Summary: Extract viewports from country codes, without the need of relying on Google APIs.
Home-page: https://ytec.nl/
Author: YTEC
Author-email: alvin@ytec.nl
License: MIT
Keywords: viewport,country
Platform: UNKNOWN
Classifier: Development Status :: 5 - Production/Stable
Classifier: Intended Audience :: Developers
Classifier: Topic :: Software Development :: Build Tools
Classifier: License :: OSI Approved :: MIT License
Classifier: Programming Language :: Python :: 3
